mem0/__init__.py
mem0/client/__init__.py
mem0/client/main.py
mem0/configs/__init__.py
mem0/configs/base.py
mem0/configs/embeddings/__init__.py
mem0/configs/embeddings/base.py
mem0/configs/llms/__init__.py
mem0/configs/llms/base.py
mem0/configs/prompts.py
mem0/configs/vector_stores/__init__.py
mem0/configs/vector_stores/chroma.py
mem0/configs/vector_stores/milvus.py
mem0/configs/vector_stores/pgvector.py
mem0/configs/vector_stores/qdrant.py
mem0/embeddings/__init__.py
mem0/embeddings/azure_openai.py
mem0/embeddings/base.py
mem0/embeddings/configs.py
mem0/embeddings/huggingface.py
mem0/embeddings/ollama.py
mem0/embeddings/openai.py
mem0/embeddings/vertexai.py
mem0/graphs/configs.py
mem0/graphs/tools.py
mem0/graphs/utils.py
mem0/llms/__init__.py
mem0/llms/anthropic.py
mem0/llms/aws_bedrock.py
mem0/llms/azure_openai.py
mem0/llms/azure_openai_structured.py
mem0/llms/base.py
mem0/llms/configs.py
mem0/llms/groq.py
mem0/llms/litellm.py
mem0/llms/ollama.py
mem0/llms/openai.py
mem0/llms/openai_structured.py
mem0/llms/together.py
mem0/llms/utils/__init__.py
mem0/llms/utils/functions.py
mem0/llms/utils/tools.py
mem0/memory/__init__.py
mem0/memory/base.py
mem0/memory/graph_memory.py
mem0/memory/main.py
mem0/memory/setup.py
mem0/memory/storage.py
mem0/memory/telemetry.py
mem0/memory/utils.py
mem0/proxy/__init__.py
mem0/proxy/main.py
mem0/utils/factory.py
mem0/vector_stores/__init__.py
mem0/vector_stores/base.py
mem0/vector_stores/chroma.py
mem0/vector_stores/configs.py
mem0/vector_stores/milvus.py
mem0/vector_stores/pgvector.py
mem0/vector_stores/qdrant.py
mem0ai_pgvector-0.1.dist-info/LICENSE
mem0ai_pgvector-0.1.dist-info/METADATA
mem0ai_pgvector-0.1.dist-info/WHEEL
mem0ai_pgvector-0.1.dist-info/RECORD
