Metadata-Version: 2.1
Name: mem0ai-pgvector
Version: 0.1
Summary: Long-term memory for AI Agents
Author: Alex
Author-email: alex@gmail.com
Requires-Python: >=3.9,<4.0
Classifier: Programming Language :: Python :: 3
Classifier: Programming Language :: Python :: 3.9
Classifier: Programming Language :: Python :: 3.10
Classifier: Programming Language :: Python :: 3.11
Classifier: Programming Language :: Python :: 3.12
Requires-Dist: langchain-community (>=0.2.12,<0.3.0)
Requires-Dist: neo4j (>=5.23.1,<6.0.0)
Requires-Dist: openai (>=1.33.0,<2.0.0)
Requires-Dist: posthog (>=3.5.0,<4.0.0)
Requires-Dist: pydantic (>=2.7.3,<3.0.0)
Requires-Dist: pytz (>=2024.1,<2025.0)
Requires-Dist: qdrant-client (>=1.9.1,<2.0.0)
Requires-Dist: rank-bm25 (>=0.2.2,<0.3.0)
Requires-Dist: sqlalchemy (>=2.0.31,<3.0.0)
